cndpolator.cpython-312-darwin.so
ndpolator-1.3.0.dist-info/RECORD
ndpolator-1.3.0.dist-info/WHEEL
ndpolator-1.3.0.dist-info/top_level.txt
ndpolator-1.3.0.dist-info/METADATA
ndpolator-1.3.0.dist-info/licenses/LICENSE
ndpolator/__init__.py
ndpolator/ndpolator.py
