Metadata-Version: 2.4
Name: ndpolator
Version: 1.3.0
Summary: ndpolator: fast, n-dimensional linear interpolation and extrapolation on sparse grids
Author-email: Andrej Prša <aprsa@villanova.edu>
Maintainer-email: Andrej Prša <aprsa@villanova.edu>
License-Expression: GPL-3.0-or-later
Project-URL: repository, https://github.com/aprsa/ndpolator
Keywords: mathematics,interpolation,extrapolation,science
Classifier: Development Status :: 5 - Production/Stable
Classifier: Environment :: Console
Classifier: Intended Audience :: Developers
Classifier: Intended Audience :: Science/Research
Classifier: Natural Language :: English
Classifier: Operating System :: OS Independent
Classifier: Programming Language :: C
Classifier: Programming Language :: Python :: 3
Classifier: Topic :: Scientific/Engineering
Classifier: Topic :: Scientific/Engineering :: Mathematics
Classifier: Topic :: Software Development :: Libraries
Classifier: Topic :: Utilities
Requires-Python: >=3.9
License-File: LICENSE
Requires-Dist: numpy
Provides-Extra: test
Requires-Dist: pytest; extra == "test"
Provides-Extra: dev
Requires-Dist: pytest; extra == "dev"
Dynamic: license-file
